examples/__init__.py
examples/benchmark_example.py
lra_benchmark/__init__.py
lra_benchmark/benchmark.py
lra_benchmark/config.py
lra_benchmark/dataset.py
lra_benchmark/models/__init__.py
lra_benchmark/models/base_model.py
lra_benchmark/models/nano_vit.py
lra_benchmark/models/pico_vit.py
lra_benchmark/models/tiny_vit.py
lra_benchmark/utils/__init__.py
lra_benchmark/utils/optimizer.py
tests/__init__.py
tests/test_benchmark.py
tests/test_models.py
lra_benchmark-0.1.3.dist-info/LICENSE
lra_benchmark-0.1.3.dist-info/METADATA
lra_benchmark-0.1.3.dist-info/WHEEL
lra_benchmark-0.1.3.dist-info/top_level.txt
lra_benchmark-0.1.3.dist-info/RECORD
