Metadata-Version: 2.1
Name: lra-benchmark
Version: 0.1.3
Summary: A library for benchmarking lightweight Vision Transformers following the LRA methodology
Home-page: https://github.com/SamiAGOURRAM/LRA-Benchmark-for-image-classification-on-CIFAR-10.git
Author: Sami Agourram
Author-email: agourram.ma@gmail.com
License: UNKNOWN
Platform: UNKNOWN
Classifier: Development Status :: 3 - Alpha
Classifier: Intended Audience :: Developers
Classifier: Intended Audience :: Education
Classifier: Intended Audience :: Science/Research
Classifier: License :: OSI Approved :: MIT License
Classifier: Programming Language :: Python :: 3
Classifier: Programming Language :: Python :: 3.7
Classifier: Programming Language :: Python :: 3.8
Classifier: Programming Language :: Python :: 3.9
Classifier: Topic :: Scientific/Engineering :: Artificial Intelligence
Classifier: Topic :: Software Development :: Libraries :: Python Modules
Requires-Python: >=3.7
License-File: LICENSE
Requires-Dist: torch
Requires-Dist: torchvision
Requires-Dist: timm
Requires-Dist: pytorch-lightning
